ohmyds/__init__.py
ohmyds/binary_tree/__init__.py
ohmyds/binary_tree/tree.py
ohmyds-0.0.2.dist-info/LICENSE
ohmyds-0.0.2.dist-info/METADATA
ohmyds-0.0.2.dist-info/WHEEL
ohmyds-0.0.2.dist-info/top_level.txt
ohmyds-0.0.2.dist-info/RECORD
